gnome_recent_files_cleaner.py
gnome_recent_files_cleaner-0.2.dist-info/LICENSE
gnome_recent_files_cleaner-0.2.dist-info/METADATA
gnome_recent_files_cleaner-0.2.dist-info/WHEEL
gnome_recent_files_cleaner-0.2.dist-info/top_level.txt
gnome_recent_files_cleaner-0.2.dist-info/RECORD
