Metadata-Version: 2.1
Name: gnome-recent-files-cleaner
Version: 0.2
Summary: Cleans your recent files from anything that is hidden or located within a hidden directory.
Home-page: https://github.com/joka42/recent-files-cleaner
Author: Jonas Kalinka
Author-email: jonas.kalinka@web.de
License: UNKNOWN
Project-URL: Bug Tracker, https://github.com/joka42/recent-files-cleaner/issues
Platform: UNKNOWN
Classifier: Programming Language :: Python :: 3
Classifier: License :: OSI Approved :: GNU General Public License v3 or later (GPLv3+)
Classifier: Operating System :: OS Independent
Requires-Python: >=3.6
License-File: LICENSE
Requires-Dist: watchdog
